zeughaus_mcp/__init__.py
zeughaus_mcp-0.1.4.dist-info/METADATA
zeughaus_mcp-0.1.4.dist-info/WHEEL
zeughaus_mcp-0.1.4.dist-info/entry_points.txt
zeughaus_mcp-0.1.4.dist-info/RECORD
