Metadata-Version: 2.4
Name: zeughaus-mcp
Version: 0.1.4
Summary: MCP Server - Agentic Workbench backed by Nixery
Project-URL: Homepage, https://github.com/GTarkin/zeughaus_mcp
Project-URL: Repository, https://github.com/GTarkin/zeughaus_mcp
Author: GTarkin
License-Expression: MIT
Requires-Python: >=3.10
Requires-Dist: docker>=7.0.0
Requires-Dist: fastmcp>=2.0.0
Requires-Dist: pydantic-settings>=2.0.0
